Workbook

Sheet Inputs
A1: Laro Pets — unit economics inputs
A2: Legend: blue text = input you can change · yellow fill = assumption to confirm before launch · black = formula. Prices come from content/product.ts; change them there and on the Tiers sheet together.
A4: Sourcing case (USD per unit) | B4: Low (bulk) | C4: Typical (single) | D4: High (CJ fast) | E4: Source / note
A5: Product cost | B5: 3.8 | C5: 6.87 | D5: 10 | E5: research/pricing.md (agent report, 3 Sep 2026): Alibaba bulk $3.80 / AliExpress single $6.87 / premium or CJ fast line $10.00
A6: Inbound shipping per unit | B6: 1 | C6: 2 | D6: 3.5 | E6: research/pricing.md (agent report, 3 Sep 2026): consolidated freight vs single parcel vs CJ fast line
A7: Platform / payment fees on the purchase | B7: 0.04 | C7: 0.04 | D7: 0.04 | E7: research/pricing.md (agent report, 3 Sep 2026): ~4% of product + shipping
A8: Landed cost per mat (USD) | B8: =(B5+B6)*(1+B7) -> 4.992 | C8: =(C5+C6)*(1+C7) -> 9.2248 | D8: =(D5+D6)*(1+D7) -> 14.04 | E8: Formula: (product + shipping) × (1 + fees). Reproduces the ₱312 / ₱577 / ₱878 landed-cost table in the research.
A9: Landed cost per mat (PHP) | B9: =B8*$B$12 -> 312.14976 | C9: =C8*$B$12 -> 576.82674 | D9: =D8*$B$12 -> 877.9212
A11: Global assumptions | B11: Value | E11: Source / note
A12: FX rate (PHP per USD) | B12: 62.53 | E12: research/pricing.md (agent report, 3 Sep 2026): XE mid-market, 3 Sep 2026
A13: Sourcing case used on the Tiers sheet (1 = Low, 2 = Typical, 3 = High) | B13: 1 | E13: Picks the column of the table above. Bulk (1) is the only case where ₱799 clears the research’s 2.5× rule.
A14: Feather refill pack cost, 3 feathers (PHP) | B14: 45 | E14: research/pricing.md (agent report, 3 Sep 2026): ₱15–19 per feather → 3-pack ≈ ₱45 landed
A15: Packaging + insert per order (PHP) | B15: 15 | E15: ASSUMPTION: mailer bag, tape, quick-start card. Replace with your supplier quote.
A16: Courier zone used on the Tiers sheet (1 = Metro Manila, 2 = Provinces) | B16: 1 | E16: Switch to see provincial economics.
A17: Courier cost — Metro Manila, up to 1 kg (PHP) | B17: 85 | E17: ASSUMPTION — confirm with your J&T / Flash / LBC merchant rate card. Shopee-subsidised rates (₱39–49) do NOT apply to direct shipping.
A18: Courier cost — Provinces, up to 1 kg (PHP) | B18: 150 | E18: ASSUMPTION — confirm with the courier rate card (often ₱130–180).
A19: COD collection fee (% of amount collected) | B19: 0.02 | E19: ASSUMPTION — merchant COD fees are typically 1.5–3%. Shopee reference: ₱25/order + 1.5%.
A20: COD fixed fee per order (PHP) | B20: 0 | E20: Set if your courier charges a per-parcel COD fee.
A21: Payment method used on the Tiers sheet (1 = COD, 2 = GCash/Maya, 3 = Card) | B21: 1 | E21: Most PH first orders are COD.
A22: PayMongo e-wallet fee, GCash / Maya (%) | B22: 0.025 | E22: ASSUMPTION — PayMongo published rate ≈ 2.5% (+ VAT on the fee); confirm in your dashboard.
A23: PayMongo card fee (%) | B23: 0.035 | E23: ASSUMPTION — ≈ 3.5% + ₱15 (+ VAT on the fee); confirm.
... A26: Target contribution margin before ads (%) | B26: 0.4 | E26: Your choice: the share of revenue that must survive product, shipping and fees before any ad spend.
A28: Selected landed cost per mat (PHP) | B28: =INDEX($B$9:$D$9,1,Inputs!$B$13) -> 312.14976 | E28: Formula: the landed-cost column chosen in B13.
A29: Selected courier cost per order (PHP) | B29: =IF(Inputs!$B$16=1,Inputs!$B$17,Inputs!$B$18) -> 85

Sheet Tiers
A1: Contribution margin per order, by bundle
A2: ="Sourcing: "&IF(Inputs!$B$13=1,"Low (bulk)",IF(Inputs!$B$13=2,"Typical (single)","High (CJ fast)"))&" · Zone: "&IF(Inputs!$B$16=1,"Metro Manila","Provinces")&" · Payment: "&IF(Inputs!$B$21=1,"Cash on Delivery",IF(Inputs!$B$21=2,"GCash / Maya","Card")) -> Sourcing: Low (bulk) · Zone: Metro Manila · Payment: Cash on Delivery
A4: Line | B4: Solo Play | C4: Mat + Refill | D4: Multi-Cat Home | E4: How it is computed
A5: Price charged (PHP) | B5: 799 | C5: 899 | D5: 1679 | E5: content/product.ts prices — change there and here together
A6: Mats in the box | B6: 1 | C6: 1 | D6: 2 | E6: content/product.ts tiers[].mats
A7: Refill packs included | B7: 0 | C7: 1 | D7: 1 | E7: content/product.ts tiers[].refillsIncluded
A8: Shipping fee charged to the customer (PHP) | B8: 79 | C8: 0 | D8: 0 | E8: lib/pricing.ts: ₱79 below ₱899, free at ₱899+
A9: Revenue per order (price + shipping fee) | B9: =B5+B8 -> 878 | C9: =C5+C8 -> 899 | D9: =D5+D8 -> 1679 | E9: price + shipping charged
A10: Product cost (mats × landed) | B10: =B6*Inputs!$B$28 -> 312.14976 | C10: =C6*Inputs!$B$28 -> 312.14976 | D10: =D6*Inputs!$B$28 -> 624.29952 | E10: Inputs B28 (selected sourcing case)
A11: Refill packs cost | B11: =B7*Inputs!$B$14 -> 0 | C11: =C7*Inputs!$B$14 -> 45 | D11: =D7*Inputs!$B$14 -> 45 | E11: Inputs B14
A12: Packaging | B12: =Inputs!$B$15 -> 15 | C12: =Inputs!$B$15 -> 15 | D12: =Inputs!$B$15 -> 15 | E12: Inputs B15
A13: Courier cost | B13: =Inputs!$B$29 -> 85 | C13: =Inputs!$B$29 -> 85 | D13: =Inputs!$B$29 -> 85 | E13: Inputs B29 (selected zone). Multi-Cat may exceed 1 kg — check the rate card.
A14: Payment / COD fees | B14: =IF(Inputs!$B$21=1,B9*Inputs!$B$19+Inputs!$B$20,IF(Inputs!$B$21=2,B9*Inputs!$B$22,B9*Inputs!$B$23+Inputs!$B$24)) -> 17.56 | C14: =IF(Inputs!$B$21=1,C9*Inputs!$B$19+Inputs!$B$20,IF(Inputs!$B$21=2,C9*Inputs!$B$22,C9*Inputs!$B$23+Inputs!$B$24)) -> 17.98 | D14: =IF(Inputs!$B$21=1,D9*Inputs!$B$19+Inputs!$B$20,IF(Inputs!$B$21=2,D9*Inputs!$B$22,D9*Inputs!$B$23+Inputs!$B$24)) -> 33.58 | E14: COD % + fixed, or PayMongo e-wallet %, or card % + fixed, applied to revenue
A15: Returns + warranty reserve | B15: =B5*Inputs!$B$25 -> 31.96 | C15: =C5*Inputs!$B$25 -> 35.96 | D15: =D5*Inputs!$B$25 -> 67.16 | E15: Inputs B25 × price
A16: Total cost per order | B16: =SUM(B10:B15) -> 461.66976 | C16: =SUM(C10:C15) -> 511.08976 | D16: =SUM(D10:D15) -> 870.03952 | E16: sum of the six cost lines
A17: Contribution per order (PHP) | B17: =B9-B16 -> 416.33024 | C17: =C9-C16 -> 387.91024 | D17: =D9-D16 -> 808.96048 | E17: revenue − total cost, before ads and fixed costs
A18: Contribution margin (% of revenue) | B18: =IF(B9=0,0,B17/B9) -> 0.47418023 | C18: =IF(C9=0,0,C17/C9) -> 0.43149081 | D18: =IF(D9=0,0,D17/D9) -> 0.48181089
A19: Price ÷ landed product cost | B19: =IF(B10=0,0,B5/B10) -> 2.5596688 | C19: =IF(C10=0,0,C5/C10) -> 2.8800278 | D19: =IF(D10=0,0,D5/D10) -> 2.6894142 | E19: the research targets ≥ 2.5×
A20: Max ad spend per order at the target margin | B20: =B17-B9*Inputs!$B$26 -> 65.13024 | C20: =C17-C9*Inputs!$B$26 -> 28.31024 | D20: =D17-D9*Inputs!$B$26 -> 137.36048 | E20: contribution − target margin × revenue; negative means the price cannot carry that target
A21: Orders per month to cover ₱10,000 of fixed costs | B21: =IF(B17<=0,"n/a",ROUNDUP(10000/B17,0)) -> 25 | C21: =IF(C17<=0,"n/a",ROUNDUP(10000/C17,0)) -> 26 | D21: =IF(D17<=0,"n/a",ROUNDUP(10000/D17,0)) -> 13 | E21: subscriptions, packaging stock, etc.

Sheet Scenarios
A1: Mat + Refill (₱899, free shipping), Cash on Delivery — every sourcing case at once
A2: Same cost lines as the Tiers sheet, evaluated for all three sourcing cases and both zones, so the whole picture is visible without flipping inputs.
A4: Metric | B4: Low (bulk) | C4: Typical (single) | D4: High (CJ fast)
A5: Landed cost per mat | B5: =Inputs!B9 -> 312.14976 | C5: =Inputs!C9 -> 576.82674 | D5: =Inputs!D9 -> 877.9212
A6: Contribution per order — Metro Manila | B6: =(Tiers!$C$5+Tiers!$C$8)-(Tiers!$C$6*Inputs!B9+Tiers!$C$7*Inputs!$B$14+Inputs!$B$15+Inputs!$B$17+(Tiers!$C$5+Tiers!$C$8)*Inputs!$B$19+Inputs!$B$20+Tiers!$C$5*Inputs!$B$25) -> 387.91024 | C6: =(Tiers!$C$5+Tiers!$C$8)-(Tiers!$C$6*Inputs!C9+Tiers!$C$7*Inputs!$B$14+Inputs!$B$15+Inputs!$B$17+(Tiers!$C$5+Tiers!$C$8)*Inputs!$B$19+Inputs!$B$20+Tiers!$C$5*Inputs!$B$25) -> 123.23326 | D6: =(Tiers!$C$5+Tiers!$C$8)-(Tiers!$C$6*Inputs!D9+Tiers!$C$7*Inputs!$B$14+Inputs!$B$15+Inputs!$B$17+(Tiers!$C$5+Tiers!$C$8)*Inputs!$B$19+Inputs!$B$20+Tiers!$C$5*Inputs!$B$25) -> -177.8612
A7: Contribution per order — Provinces | B7: =(Tiers!$C$5+Tiers!$C$8)-(Tiers!$C$6*Inputs!B9+Tiers!$C$7*Inputs!$B$14+Inputs!$B$15+Inputs!$B$18+(Tiers!$C$5+Tiers!$C$8)*Inputs!$B$19+Inputs!$B$20+Tiers!$C$5*Inputs!$B$25) -> 322.91024 | C7: =(Tiers!$C$5+Tiers!$C$8)-(Tiers!$C$6*Inputs!C9+Tiers!$C$7*Inputs!$B$14+Inputs!$B$15+Inputs!$B$18+(Tiers!$C$5+Tiers!$C$8)*Inputs!$B$19+Inputs!$B$20+Tiers!$C$5*Inputs!$B$25) -> 58.233256 | D7: =(Tiers!$C$5+Tiers!$C$8)-(Tiers!$C$6*Inputs!D9+Tiers!$C$7*Inputs!$B$14+Inputs!$B$15+Inputs!$B$18+(Tiers!$C$5+Tiers!$C$8)*Inputs!$B$19+Inputs!$B$20+Tiers!$C$5*Inputs!$B$25) -> -242.8612
A8: Margin % — Metro Manila | B8: =IF((Tiers!$C$5+Tiers!$C$8)=0,0,B6/(Tiers!$C$5+Tiers!$C$8)) -> 0.43149081 | C8: =IF((Tiers!$C$5+Tiers!$C$8)=0,0,C6/(Tiers!$C$5+Tiers!$C$8)) -> 0.13707815 | D8: =IF((Tiers!$C$5+Tiers!$C$8)=0,0,D6/(Tiers!$C$5+Tiers!$C$8)) -> -0.19784338
A9: Margin % — Provinces | B9: =IF((Tiers!$C$5+Tiers!$C$8)=0,0,B7/(Tiers!$C$5+Tiers!$C$8)) -> 0.35918825 | C9: =IF((Tiers!$C$5+Tiers!$C$8)=0,0,C7/(Tiers!$C$5+Tiers!$C$8)) -> 0.064775591 | D9: =IF((Tiers!$C$5+Tiers!$C$8)=0,0,D7/(Tiers!$C$5+Tiers!$C$8)) -> -0.27014594
A10: Price ÷ landed | B10: =IF(Inputs!B9=0,0,Tiers!$C$5/Inputs!B9) -> 2.8800278 | C10: =IF(Inputs!C9=0,0,Tiers!$C$5/Inputs!C9) -> 1.5585269 | D10: =IF(Inputs!D9=0,0,Tiers!$C$5/Inputs!D9) -> 1.0240099
A12: Reading: only the bulk case keeps ₱899 near the research’s 2.5× rule. Single-unit AliExpress sourcing leaves a thin margin once courier, COD fee and the returns reserve are counted, and the high case loses money.
A14: Sources
A15: research/pricing.md (agent report, 3 Sep 2026): supplier listings, landed-cost table, Shopee fee references, BOC de minimis ₱10,000 (bulk restocks above it pay duty + 12% VAT + brokerage).
A16: Courier, COD and PayMongo fees are assumptions (yellow cells on Inputs). Replace them with your rate cards before relying on this sheet.
